<imagem>
    <grupo prof="1">
        <grupo prof="2">
            <escala X="1" Y="1" Z="1"/>
            <modelos>
                <modelo ficheiro="esfera3.3d" colorX="1.0" colorY="1.0" colorZ="0.0"/>
            </modelos>
            <grupo prof="3">
                <translacao tempo="10">
                    <ponto X="30.0" Y="0" Z="0.0"/>
                    <ponto X="29.630650217854132" Y="0" Z="4.693033951206926"/>
                    <ponto X="28.531695488854606" Y="0" Z="9.270509831248422"/>
                    <ponto X="26.730195725651036" Y="0" Z="13.619714992186402"/>
                    <ponto X="24.270509831248425" Y="0" Z="17.633557568774194"/>
                    <ponto X="21.213203435596427" Y="0" Z="21.213203435596423"/>
                    <ponto X="17.633557568774194" Y="0" Z="24.270509831248425"/>
                    <ponto X="13.619714992186406" Y="0" Z="26.730195725651033"/>
                    <ponto X="9.270509831248424" Y="0" Z="28.531695488854606"/>
                    <ponto X="4.693033951206928" Y="0" Z="29.630650217854132"/>
                    <ponto X="1.83697019872103e-15" Y="0" Z="30.0"/>
                    <ponto X="-4.693033951206925" Y="0" Z="29.630650217854132"/>
                    <ponto X="-9.27050983124842" Y="0" Z="28.53169548885461"/>
                    <ponto X="-13.6197149921864" Y="0" Z="26.730195725651036"/>
                    <ponto X="-17.63355756877419" Y="0" Z="24.270509831248425"/>
                    <ponto X="-21.213203435596423" Y="0" Z="21.213203435596427"/>
                    <ponto X="-24.27050983124842" Y="0" Z="17.633557568774197"/>
                    <ponto X="-26.730195725651033" Y="0" Z="13.619714992186406"/>
                    <ponto X="-28.531695488854606" Y="0" Z="9.270509831248425"/>
                    <ponto X="-29.63065021785413" Y="0" Z="4.693033951206929"/>
                    <ponto X="-30.0" Y="0" Z="3.67394039744206e-15"/>
                    <ponto X="-29.630650217854132" Y="0" Z="-4.693033951206922"/>
                    <ponto X="-28.53169548885461" Y="0" Z="-9.270509831248418"/>
                    <ponto X="-26.730195725651036" Y="0" Z="-13.619714992186399"/>
                    <ponto X="-24.270509831248425" Y="0" Z="-17.63355756877419"/>
                    <ponto X="-21.21320343559643" Y="0" Z="-21.213203435596423"/>
                    <ponto X="-17.633557568774197" Y="0" Z="-24.27050983124842"/>
                    <ponto X="-13.619714992186408" Y="0" Z="-26.730195725651033"/>
                    <ponto X="-9.270509831248427" Y="0" Z="-28.531695488854606"/>
                    <ponto X="-4.693033951206931" Y="0" Z="-29.63065021785413"/>
                    <ponto X="-5.510910596163089e-15" Y="0" Z="-30.0"/>
                    <ponto X="4.69303395120692" Y="0" Z="-29.630650217854132"/>
                    <ponto X="9.270509831248416" Y="0" Z="-28.53169548885461"/>
                    <ponto X="13.619714992186399" Y="0" Z="-26.73019572565104"/>
                    <ponto X="17.633557568774187" Y="0" Z="-24.270509831248425"/>
                    <ponto X="21.21320343559642" Y="0" Z="-21.21320343559643"/>
                    <ponto X="24.27050983124842" Y="0" Z="-17.6335575687742"/>
                    <ponto X="26.730195725651033" Y="0" Z="-13.61971499218641"/>
                    <ponto X="28.531695488854606" Y="0" Z="-9.27050983124843"/>
                    <ponto X="29.63065021785413" Y="0" Z="-4.693033951206933"/>
                </translacao>
				<escala X="0.08823529411764706" Y="0.08823529411764706" Z="0.08823529411764706"/>
                <rotacao tempo="10" angulo="360" eixoX="0" eixoY="1" eixoZ="0"/>
                <modelos>
                    <modelo ficheiro="esfera3.3d" colorX="0.752941" colorY="0.752941" colorZ="0.752941"
                    />
                </modelos>
            </grupo>
            <grupo prof="3">
                <escala X="0.11176470588235293" Y="0.11176470588235293" Z="0.11176470588235293"/>
                <translacao tempo="13">
                    <ponto X="45.0" Y="0" Z="0.0"/>
                    <ponto X="44.4459753267812" Y="0" Z="7.0395509268103895"/>
                    <ponto X="42.79754323328191" Y="0" Z="13.905764746872633"/>
                    <ponto X="40.09529358847656" Y="0" Z="20.429572488279604"/>
                    <ponto X="36.405764746872634" Y="0" Z="26.45033635316129"/>
                    <ponto X="31.81980515339464" Y="0" Z="31.819805153394636"/>
                    <ponto X="26.45033635316129" Y="0" Z="36.405764746872634"/>
                    <ponto X="20.429572488279607" Y="0" Z="40.09529358847655"/>
                    <ponto X="13.905764746872634" Y="0" Z="42.79754323328191"/>
                    <ponto X="7.039550926810391" Y="0" Z="44.4459753267812"/>
                    <ponto X="2.7554552980815448e-15" Y="0" Z="45.0"/>
                    <ponto X="-7.039550926810387" Y="0" Z="44.4459753267812"/>
                    <ponto X="-13.90576474687263" Y="0" Z="42.797543233281914"/>
                    <ponto X="-20.4295724882796" Y="0" Z="40.09529358847656"/>
                    <ponto X="-26.450336353161287" Y="0" Z="36.405764746872634"/>
                    <ponto X="-31.819805153394636" Y="0" Z="31.81980515339464"/>
                    <ponto X="-36.40576474687263" Y="0" Z="26.450336353161298"/>
                    <ponto X="-40.09529358847655" Y="0" Z="20.429572488279607"/>
                    <ponto X="-42.79754323328191" Y="0" Z="13.905764746872638"/>
                    <ponto X="-44.445975326781195" Y="0" Z="7.039550926810394"/>
                    <ponto X="-45.0" Y="0" Z="5.5109105961630896e-15"/>
                    <ponto X="-44.4459753267812" Y="0" Z="-7.039550926810383"/>
                    <ponto X="-42.797543233281914" Y="0" Z="-13.905764746872627"/>
                    <ponto X="-40.09529358847656" Y="0" Z="-20.4295724882796"/>
                    <ponto X="-36.405764746872634" Y="0" Z="-26.450336353161287"/>
                    <ponto X="-31.819805153394647" Y="0" Z="-31.819805153394636"/>
                    <ponto X="-26.450336353161298" Y="0" Z="-36.40576474687263"/>
                    <ponto X="-20.42957248827961" Y="0" Z="-40.09529358847655"/>
                    <ponto X="-13.90576474687264" Y="0" Z="-42.79754323328191"/>
                    <ponto X="-7.039550926810397" Y="0" Z="-44.445975326781195"/>
                    <ponto X="-8.266365894244634e-15" Y="0" Z="-45.0"/>
                    <ponto X="7.039550926810381" Y="0" Z="-44.4459753267812"/>
                    <ponto X="13.905764746872626" Y="0" Z="-42.797543233281914"/>
                    <ponto X="20.4295724882796" Y="0" Z="-40.09529358847656"/>
                    <ponto X="26.45033635316128" Y="0" Z="-36.40576474687264"/>
                    <ponto X="31.81980515339463" Y="0" Z="-31.819805153394647"/>
                    <ponto X="36.40576474687263" Y="0" Z="-26.4503363531613"/>
                    <ponto X="40.09529358847655" Y="0" Z="-20.429572488279614"/>
                    <ponto X="42.79754323328191" Y="0" Z="-13.905764746872645"/>
                    <ponto X="44.445975326781195" Y="0" Z="-7.039550926810399"/>
                </translacao>
                <rotacao tempo="10" angulo="360" eixoX="0" eixoY="1" eixoZ="0"/>
                <modelos>
                    <modelo ficheiro="esfera3.3d" colorX="1.0" colorY="0.5" colorZ="0.0"/>
                </modelos>
            </grupo>
            <grupo prof="3">
                <escala X="0.11764705882352941" Y="0.11764705882352941" Z="0.11764705882352941"/>
                <translacao tempo="15">
                    <ponto X="60.0" Y="0" Z="0.0"/>
                    <ponto X="59.261300435708264" Y="0" Z="9.386067902413853"/>
                    <ponto X="57.06339097770921" Y="0" Z="18.541019662496844"/>
                    <ponto X="53.46039145130207" Y="0" Z="27.239429984372805"/>
                    <ponto X="48.54101966249685" Y="0" Z="35.26711513754839"/>
                    <ponto X="42.42640687119285" Y="0" Z="42.426406871192846"/>
                    <ponto X="35.26711513754839" Y="0" Z="48.54101966249685"/>
                    <ponto X="27.239429984372812" Y="0" Z="53.460391451302065"/>
                    <ponto X="18.541019662496847" Y="0" Z="57.06339097770921"/>
                    <ponto X="9.386067902413856" Y="0" Z="59.261300435708264"/>
                    <ponto X="3.67394039744206e-15" Y="0" Z="60.0"/>
                    <ponto X="-9.38606790241385" Y="0" Z="59.261300435708264"/>
                    <ponto X="-18.54101966249684" Y="0" Z="57.06339097770922"/>
                    <ponto X="-27.2394299843728" Y="0" Z="53.46039145130207"/>
                    <ponto X="-35.26711513754838" Y="0" Z="48.54101966249685"/>
                    <ponto X="-42.426406871192846" Y="0" Z="42.42640687119285"/>
                    <ponto X="-48.54101966249684" Y="0" Z="35.267115137548394"/>
                    <ponto X="-53.460391451302065" Y="0" Z="27.239429984372812"/>
                    <ponto X="-57.06339097770921" Y="0" Z="18.54101966249685"/>
                    <ponto X="-59.26130043570826" Y="0" Z="9.386067902413858"/>
                    <ponto X="-60.0" Y="0" Z="7.34788079488412e-15"/>
                    <ponto X="-59.261300435708264" Y="0" Z="-9.386067902413844"/>
                    <ponto X="-57.06339097770922" Y="0" Z="-18.541019662496836"/>
                    <ponto X="-53.46039145130207" Y="0" Z="-27.239429984372798"/>
                    <ponto X="-48.54101966249685" Y="0" Z="-35.26711513754838"/>
                    <ponto X="-42.42640687119286" Y="0" Z="-42.426406871192846"/>
                    <ponto X="-35.267115137548394" Y="0" Z="-48.54101966249684"/>
                    <ponto X="-27.239429984372816" Y="0" Z="-53.460391451302065"/>
                    <ponto X="-18.541019662496854" Y="0" Z="-57.06339097770921"/>
                    <ponto X="-9.386067902413862" Y="0" Z="-59.26130043570826"/>
                    <ponto X="-1.1021821192326178e-14" Y="0" Z="-60.0"/>
                    <ponto X="9.38606790241384" Y="0" Z="-59.261300435708264"/>
                    <ponto X="18.541019662496833" Y="0" Z="-57.06339097770922"/>
                    <ponto X="27.239429984372798" Y="0" Z="-53.46039145130208"/>
                    <ponto X="35.26711513754837" Y="0" Z="-48.54101966249685"/>
                    <ponto X="42.42640687119284" Y="0" Z="-42.42640687119286"/>
                    <ponto X="48.54101966249684" Y="0" Z="-35.2671151375484"/>
                    <ponto X="53.460391451302065" Y="0" Z="-27.23942998437282"/>
                    <ponto X="57.06339097770921" Y="0" Z="-18.54101966249686"/>
                    <ponto X="59.26130043570826" Y="0" Z="-9.386067902413865"/>
                </translacao>
                <rotacao tempo="10" angulo="360" eixoX="0" eixoY="1" eixoZ="0"/>
                <modelos>
                    <modelo ficheiro="esfera3.3d" colorX="0.0" colorY="0.0" colorZ="1.0"/>
                </modelos>
            </grupo>
            <grupo prof="3">
                <escala X="0.09411764705882353" Y="0.09411764705882353" Z="0.09411764705882353"/>
                <translacao tempo="17">
                    <ponto X="70.0" Y="0" Z="0.0"/>
                    <ponto X="69.13818384165964" Y="0" Z="10.95041255281616"/>
                    <ponto X="66.57395614066074" Y="0" Z="21.631189606246316"/>
                    <ponto X="62.37045669318575" Y="0" Z="31.779334981768272"/>
                    <ponto X="56.63118960624632" Y="0" Z="41.14496766047312"/>
                    <ponto X="49.49747468305833" Y="0" Z="49.49747468305832"/>
                    <ponto X="41.14496766047312" Y="0" Z="56.63118960624632"/>
                    <ponto X="31.77933498176828" Y="0" Z="62.370456693185744"/>
                    <ponto X="21.631189606246323" Y="0" Z="66.57395614066074"/>
                    <ponto X="10.950412552816164" Y="0" Z="69.13818384165964"/>
                    <ponto X="4.2862637970157365e-15" Y="0" Z="70.0"/>
                    <ponto X="-10.950412552816157" Y="0" Z="69.13818384165964"/>
                    <ponto X="-21.631189606246313" Y="0" Z="66.57395614066075"/>
                    <ponto X="-31.77933498176827" Y="0" Z="62.37045669318575"/>
                    <ponto X="-41.144967660473114" Y="0" Z="56.63118960624632"/>
                    <ponto X="-49.49747468305832" Y="0" Z="49.49747468305833"/>
                    <ponto X="-56.631189606246316" Y="0" Z="41.14496766047313"/>
                    <ponto X="-62.370456693185744" Y="0" Z="31.77933498176828"/>
                    <ponto X="-66.57395614066074" Y="0" Z="21.631189606246327"/>
                    <ponto X="-69.13818384165964" Y="0" Z="10.950412552816168"/>
                    <ponto X="-70.0" Y="0" Z="8.572527594031473e-15"/>
                    <ponto X="-69.13818384165964" Y="0" Z="-10.95041255281615"/>
                    <ponto X="-66.57395614066075" Y="0" Z="-21.63118960624631"/>
                    <ponto X="-62.37045669318575" Y="0" Z="-31.779334981768265"/>
                    <ponto X="-56.63118960624632" Y="0" Z="-41.144967660473114"/>
                    <ponto X="-49.497474683058336" Y="0" Z="-49.49747468305832"/>
                    <ponto X="-41.14496766047313" Y="0" Z="-56.631189606246316"/>
                    <ponto X="-31.779334981768283" Y="0" Z="-62.370456693185744"/>
                    <ponto X="-21.63118960624633" Y="0" Z="-66.57395614066074"/>
                    <ponto X="-10.950412552816173" Y="0" Z="-69.13818384165964"/>
                    <ponto X="-1.2858791391047208e-14" Y="0" Z="-70.0"/>
                    <ponto X="10.950412552816147" Y="0" Z="-69.13818384165964"/>
                    <ponto X="21.631189606246306" Y="0" Z="-66.57395614066075"/>
                    <ponto X="31.779334981768265" Y="0" Z="-62.37045669318576"/>
                    <ponto X="41.14496766047311" Y="0" Z="-56.63118960624633"/>
                    <ponto X="49.497474683058314" Y="0" Z="-49.497474683058336"/>
                    <ponto X="56.631189606246316" Y="0" Z="-41.144967660473135"/>
                    <ponto X="62.370456693185744" Y="0" Z="-31.779334981768287"/>
                    <ponto X="66.57395614066074" Y="0" Z="-21.631189606246338"/>
                    <ponto X="69.13818384165964" Y="0" Z="-10.950412552816177"/>
                </translacao>
                <rotacao tempo="10" angulo="360" eixoX="0" eixoY="1" eixoZ="0"/>
                <modelos>
                    <modelo ficheiro="esfera3.3d" colorX="1.0" colorY="0.0" colorZ="0.0"/>
                </modelos>
            </grupo>
            <grupo prof="3">
                <escala X="0.5294117647058824" Y="0.5294117647058824" Z="0.5294117647058824"/>
                <translacao tempo="19">
                    <ponto X="120.0" Y="0" Z="0.0"/>
                    <ponto X="118.52260087141653" Y="0" Z="18.772135804827705"/>
                    <ponto X="114.12678195541842" Y="0" Z="37.08203932499369"/>
                    <ponto X="106.92078290260415" Y="0" Z="54.47885996874561"/>
                    <ponto X="97.0820393249937" Y="0" Z="70.53423027509677"/>
                    <ponto X="84.8528137423857" Y="0" Z="84.85281374238569"/>
                    <ponto X="70.53423027509677" Y="0" Z="97.0820393249937"/>
                    <ponto X="54.478859968745624" Y="0" Z="106.92078290260413"/>
                    <ponto X="37.082039324993694" Y="0" Z="114.12678195541842"/>
                    <ponto X="18.772135804827712" Y="0" Z="118.52260087141653"/>
                    <ponto X="7.34788079488412e-15" Y="0" Z="120.0"/>
                    <ponto X="-18.7721358048277" Y="0" Z="118.52260087141653"/>
                    <ponto X="-37.08203932499368" Y="0" Z="114.12678195541844"/>
                    <ponto X="-54.4788599687456" Y="0" Z="106.92078290260415"/>
                    <ponto X="-70.53423027509676" Y="0" Z="97.0820393249937"/>
                    <ponto X="-84.85281374238569" Y="0" Z="84.8528137423857"/>
                    <ponto X="-97.08203932499369" Y="0" Z="70.53423027509679"/>
                    <ponto X="-106.92078290260413" Y="0" Z="54.478859968745624"/>
                    <ponto X="-114.12678195541842" Y="0" Z="37.0820393249937"/>
                    <ponto X="-118.52260087141651" Y="0" Z="18.772135804827716"/>
                    <ponto X="-120.0" Y="0" Z="1.469576158976824e-14"/>
                    <ponto X="-118.52260087141653" Y="0" Z="-18.772135804827688"/>
                    <ponto X="-114.12678195541844" Y="0" Z="-37.08203932499367"/>
                    <ponto X="-106.92078290260415" Y="0" Z="-54.478859968745596"/>
                    <ponto X="-97.0820393249937" Y="0" Z="-70.53423027509676"/>
                    <ponto X="-84.85281374238572" Y="0" Z="-84.85281374238569"/>
                    <ponto X="-70.53423027509679" Y="0" Z="-97.08203932499369"/>
                    <ponto X="-54.47885996874563" Y="0" Z="-106.92078290260413"/>
                    <ponto X="-37.08203932499371" Y="0" Z="-114.12678195541842"/>
                    <ponto X="-18.772135804827723" Y="0" Z="-118.52260087141651"/>
                    <ponto X="-2.2043642384652355e-14" Y="0" Z="-120.0"/>
                    <ponto X="18.77213580482768" Y="0" Z="-118.52260087141653"/>
                    <ponto X="37.082039324993666" Y="0" Z="-114.12678195541844"/>
                    <ponto X="54.478859968745596" Y="0" Z="-106.92078290260416"/>
                    <ponto X="70.53423027509675" Y="0" Z="-97.0820393249937"/>
                    <ponto X="84.85281374238568" Y="0" Z="-84.85281374238572"/>
                    <ponto X="97.08203932499369" Y="0" Z="-70.5342302750968"/>
                    <ponto X="106.92078290260413" Y="0" Z="-54.47885996874564"/>
                    <ponto X="114.12678195541842" Y="0" Z="-37.08203932499372"/>
                    <ponto X="118.52260087141651" Y="0" Z="-18.77213580482773"/>
                </translacao>
                <rotacao tempo="10" angulo="360" eixoX="0" eixoY="1" eixoZ="0"/>
                <modelos>
                    <modelo ficheiro="esfera3.3d" colorX="0.752941" colorY="0.55" colorZ="0.0"/>
                </modelos>
            </grupo>
            <grupo prof="3">
                <escala X="0.47058823529411764" Y="0.47058823529411764" Z="0.47058823529411764"/>
                <translacao tempo="20">
                    <ponto X="155.0" Y="0" Z="0.0"/>
                    <ponto X="153.09169279224636" Y="0" Z="24.247342081235786"/>
                    <ponto X="147.4137600257488" Y="0" Z="47.89763412811685"/>
                    <ponto X="138.10601124919702" Y="0" Z="70.36852745962975"/>
                    <ponto X="125.39763412811685" Y="0" Z="91.10671410533334"/>
                    <ponto X="109.60155108391487" Y="0" Z="109.60155108391486"/>
                    <ponto X="91.10671410533334" Y="0" Z="125.39763412811685"/>
                    <ponto X="70.36852745962976" Y="0" Z="138.106011249197"/>
                    <ponto X="47.897634128116856" Y="0" Z="147.4137600257488"/>
                    <ponto X="24.247342081235793" Y="0" Z="153.09169279224636"/>
                    <ponto X="9.491012693391987e-15" Y="0" Z="155.0"/>
                    <ponto X="-24.247342081235775" Y="0" Z="153.09169279224636"/>
                    <ponto X="-47.897634128116835" Y="0" Z="147.41376002574881"/>
                    <ponto X="-70.36852745962973" Y="0" Z="138.10601124919702"/>
                    <ponto X="-91.10671410533332" Y="0" Z="125.39763412811685"/>
                    <ponto X="-109.60155108391486" Y="0" Z="109.60155108391487"/>
                    <ponto X="-125.39763412811683" Y="0" Z="91.10671410533335"/>
                    <ponto X="-138.106011249197" Y="0" Z="70.36852745962976"/>
                    <ponto X="-147.4137600257488" Y="0" Z="47.89763412811686"/>
                    <ponto X="-153.09169279224633" Y="0" Z="24.247342081235804"/>
                    <ponto X="-155.0" Y="0" Z="1.8982025386783973e-14"/>
                    <ponto X="-153.09169279224636" Y="0" Z="-24.247342081235765"/>
                    <ponto X="-147.41376002574881" Y="0" Z="-47.89763412811683"/>
                    <ponto X="-138.10601124919702" Y="0" Z="-70.36852745962973"/>
                    <ponto X="-125.39763412811685" Y="0" Z="-91.10671410533332"/>
                    <ponto X="-109.60155108391488" Y="0" Z="-109.60155108391486"/>
                    <ponto X="-91.10671410533335" Y="0" Z="-125.39763412811683"/>
                    <ponto X="-70.36852745962977" Y="0" Z="-138.106011249197"/>
                    <ponto X="-47.89763412811687" Y="0" Z="-147.4137600257488"/>
                    <ponto X="-24.24734208123581" Y="0" Z="-153.09169279224633"/>
                    <ponto X="-2.847303808017596e-14" Y="0" Z="-155.0"/>
                    <ponto X="24.247342081235754" Y="0" Z="-153.09169279224636"/>
                    <ponto X="47.89763412811682" Y="0" Z="-147.41376002574881"/>
                    <ponto X="70.36852745962973" Y="0" Z="-138.10601124919705"/>
                    <ponto X="91.1067141053333" Y="0" Z="-125.39763412811688"/>
                    <ponto X="109.60155108391484" Y="0" Z="-109.60155108391488"/>
                    <ponto X="125.39763412811683" Y="0" Z="-91.10671410533337"/>
                    <ponto X="138.106011249197" Y="0" Z="-70.36852745962977"/>
                    <ponto X="147.4137600257488" Y="0" Z="-47.89763412811689"/>
                    <ponto X="153.09169279224633" Y="0" Z="-24.247342081235818"/>
                </translacao>
                <rotacao tempo="10" angulo="360" eixoX="0" eixoY="1" eixoZ="0"/>
                <modelos>
                    <modelo ficheiro="esfera3.3d" colorX="0.752941" colorY="0.6" colorZ="0.0"/>
                </modelos>
            </grupo>
            <grupo prof="3">
                <escala X="0.27647058823529413" Y="0.27647058823529413" Z="0.27647058823529413"/>
                <translacao tempo="21">
                    <ponto X="170.0" Y="0" Z="0.0"/>
                    <ponto X="167.90701790117342" Y="0" Z="26.593859056839246"/>
                    <ponto X="161.6796077701761" Y="0" Z="52.53288904374106"/>
                    <ponto X="151.47110911202253" Y="0" Z="77.17838495572295"/>
                    <ponto X="137.53288904374108" Y="0" Z="99.92349288972044"/>
                    <ponto X="120.20815280171308" Y="0" Z="120.20815280171307"/>
                    <ponto X="99.92349288972044" Y="0" Z="137.53288904374108"/>
                    <ponto X="77.17838495572296" Y="0" Z="151.47110911202253"/>
                    <ponto X="52.532889043741065" Y="0" Z="161.6796077701761"/>
                    <ponto X="26.593859056839257" Y="0" Z="167.90701790117342"/>
                    <ponto X="1.0409497792752502e-14" Y="0" Z="170.0"/>
                    <ponto X="-26.59385905683924" Y="0" Z="167.90701790117342"/>
                    <ponto X="-52.53288904374105" Y="0" Z="161.67960777017612"/>
                    <ponto X="-77.17838495572293" Y="0" Z="151.47110911202253"/>
                    <ponto X="-99.92349288972042" Y="0" Z="137.53288904374108"/>
                    <ponto X="-120.20815280171307" Y="0" Z="120.20815280171308"/>
                    <ponto X="-137.53288904374105" Y="0" Z="99.92349288972045"/>
                    <ponto X="-151.47110911202253" Y="0" Z="77.17838495572296"/>
                    <ponto X="-161.6796077701761" Y="0" Z="52.53288904374108"/>
                    <ponto X="-167.9070179011734" Y="0" Z="26.593859056839268"/>
                    <ponto X="-170.0" Y="0" Z="2.0818995585505004e-14"/>
                    <ponto X="-167.90701790117342" Y="0" Z="-26.593859056839225"/>
                    <ponto X="-161.67960777017612" Y="0" Z="-52.53288904374104"/>
                    <ponto X="-151.47110911202253" Y="0" Z="-77.17838495572293"/>
                    <ponto X="-137.53288904374108" Y="0" Z="-99.92349288972042"/>
                    <ponto X="-120.20815280171311" Y="0" Z="-120.20815280171307"/>
                    <ponto X="-99.92349288972045" Y="0" Z="-137.53288904374105"/>
                    <ponto X="-77.17838495572298" Y="0" Z="-151.47110911202253"/>
                    <ponto X="-52.532889043741086" Y="0" Z="-161.6796077701761"/>
                    <ponto X="-26.593859056839275" Y="0" Z="-167.9070179011734"/>
                    <ponto X="-3.122849337825751e-14" Y="0" Z="-170.0"/>
                    <ponto X="26.593859056839214" Y="0" Z="-167.90701790117342"/>
                    <ponto X="52.53288904374103" Y="0" Z="-161.67960777017612"/>
                    <ponto X="77.17838495572293" Y="0" Z="-151.47110911202256"/>
                    <ponto X="99.9234928897204" Y="0" Z="-137.53288904374108"/>
                    <ponto X="120.20815280171306" Y="0" Z="-120.20815280171311"/>
                    <ponto X="137.53288904374105" Y="0" Z="-99.92349288972048"/>
                    <ponto X="151.47110911202253" Y="0" Z="-77.17838495572299"/>
                    <ponto X="161.6796077701761" Y="0" Z="-52.53288904374111"/>
                    <ponto X="167.9070179011734" Y="0" Z="-26.593859056839285"/>
                </translacao>
                <rotacao tempo="10" angulo="360" eixoX="0" eixoY="1" eixoZ="0"/>
                <modelos>
                    <modelo ficheiro="esfera3.3d" colorX="0.5" colorY="0.5" colorZ="1.0"/>
                </modelos>
            </grupo>
            <grupo prof="3">
                <escala X="0.2647058823529412" Y="0.2647058823529412" Z="0.2647058823529412"/>
                <translacao tempo="22">
                    <ponto X="215.0" Y="0" Z="0.0"/>
                    <ponto X="212.3529932279546" Y="0" Z="33.633409983649635"/>
                    <ponto X="204.477151003458" Y="0" Z="66.43865379061369"/>
                    <ponto X="191.5664027004991" Y="0" Z="97.60795744400255"/>
                    <ponto X="173.9386537906137" Y="0" Z="126.37382924288173"/>
                    <ponto X="152.02795795510772" Y="0" Z="152.0279579551077"/>
                    <ponto X="126.37382924288173" Y="0" Z="173.9386537906137"/>
                    <ponto X="97.60795744400258" Y="0" Z="191.56640270049908"/>
                    <ponto X="66.4386537906137" Y="0" Z="204.477151003458"/>
                    <ponto X="33.63340998364965" Y="0" Z="212.3529932279546"/>
                    <ponto X="1.3164953090834047e-14" Y="0" Z="215.0"/>
                    <ponto X="-33.63340998364963" Y="0" Z="212.3529932279546"/>
                    <ponto X="-66.43865379061369" Y="0" Z="204.47715100345803"/>
                    <ponto X="-97.60795744400254" Y="0" Z="191.5664027004991"/>
                    <ponto X="-126.3738292428817" Y="0" Z="173.9386537906137"/>
                    <ponto X="-152.0279579551077" Y="0" Z="152.02795795510772"/>
                    <ponto X="-173.93865379061367" Y="0" Z="126.37382924288175"/>
                    <ponto X="-191.56640270049908" Y="0" Z="97.60795744400258"/>
                    <ponto X="-204.477151003458" Y="0" Z="66.43865379061371"/>
                    <ponto X="-212.35299322795458" Y="0" Z="33.63340998364966"/>
                    <ponto X="-215.0" Y="0" Z="2.6329906181668095e-14"/>
                    <ponto X="-212.3529932279546" Y="0" Z="-33.63340998364961"/>
                    <ponto X="-204.47715100345803" Y="0" Z="-66.43865379061367"/>
                    <ponto X="-191.5664027004991" Y="0" Z="-97.60795744400252"/>
                    <ponto X="-173.9386537906137" Y="0" Z="-126.3738292428817"/>
                    <ponto X="-152.02795795510775" Y="0" Z="-152.0279579551077"/>
                    <ponto X="-126.37382924288175" Y="0" Z="-173.93865379061367"/>
                    <ponto X="-97.6079574440026" Y="0" Z="-191.56640270049908"/>
                    <ponto X="-66.43865379061373" Y="0" Z="-204.477151003458"/>
                    <ponto X="-33.63340998364967" Y="0" Z="-212.35299322795458"/>
                    <ponto X="-3.9494859272502136e-14" Y="0" Z="-215.0"/>
                    <ponto X="33.63340998364959" Y="0" Z="-212.3529932279546"/>
                    <ponto X="66.43865379061366" Y="0" Z="-204.47715100345803"/>
                    <ponto X="97.60795744400252" Y="0" Z="-191.5664027004991"/>
                    <ponto X="126.37382924288168" Y="0" Z="-173.93865379061373"/>
                    <ponto X="152.02795795510767" Y="0" Z="-152.02795795510775"/>
                    <ponto X="173.93865379061367" Y="0" Z="-126.37382924288177"/>
                    <ponto X="191.56640270049908" Y="0" Z="-97.6079574440026"/>
                    <ponto X="204.477151003458" Y="0" Z="-66.43865379061376"/>
                    <ponto X="212.35299322795458" Y="0" Z="-33.633409983649685"/>
                </translacao>
                <rotacao tempo="10" angulo="360" eixoX="0" eixoY="1" eixoZ="0"/>
                <modelos>
                    <modelo ficheiro="esfera3.3d" colorX="0.0" colorY="0.0" colorZ="0.6"/>
                </modelos>
            </grupo>
        </grupo>
    </grupo>
</imagem>
